pyopencl_extension/__init__.py
pyopencl_extension/emulation.py
pyopencl_extension/framework.py
pyopencl_extension/components/__init__.py
pyopencl_extension/components/copy_array_region.py
pyopencl_extension/components/fft.py
pyopencl_extension/components/pytest.ini
pyopencl_extension/components/sumalongaxis.py
pyopencl_extension/components/transpose.py
pyopencl_extension/helpers/__init__.py
pyopencl_extension/helpers/general.py
pyopencl_extension/helpers/setup_pyopencl.py
pyopencl_extension/modifications_pyopencl/__init__.py
pyopencl_extension/modifications_pyopencl/array.py
pyopencl_extension/modifications_pyopencl/cltypes.py
pyopencl_extension/modifications_pyopencl/command_queue.py
pyopencl_extension/modifications_pyopencl/context.py
pyopencl_extension/types/__init__.py
pyopencl_extension/types/funcs_for_emulation.py
pyopencl_extension/types/type_handler.py
pyopencl_extension/types/utilities_np_cl.py
pyopencl_extension/types/auto_gen/__init__.py
pyopencl_extension/types/auto_gen/cl_types.py
pyopencl_extension/types/auto_gen/cl_types_import.py
pyopencl_extension/types/auto_gen/generate_files.py
pyopencl_extension/types/auto_gen/types_for_emulation.py
pyopencl_extension-0.2.9.dist-info/LICENSE
pyopencl_extension-0.2.9.dist-info/METADATA
pyopencl_extension-0.2.9.dist-info/WHEEL
pyopencl_extension-0.2.9.dist-info/top_level.txt
pyopencl_extension-0.2.9.dist-info/RECORD
