Metadata-Version: 2.1
Name: pyopencl-extension
Version: 0.2.9
Summary: This package extends PyOpenCl by providing an object-oriented kernel programming framework and debugging capabilities.
Home-page: https://github.com/philipp-mohr/pyopencl-extension
Author: P.Mohr
Author-email: philipp.mohr@tuhh.de
License: MIT
Platform: UNKNOWN
Classifier: License :: OSI Approved :: MIT License
Classifier: Programming Language :: Python
Classifier: Programming Language :: Python :: 3.10
Classifier: Programming Language :: Python :: Implementation :: CPython
Classifier: Programming Language :: Python :: Implementation :: PyPy
Requires-Python: >=3.10.0
License-File: LICENSE
Requires-Dist: numpy
Requires-Dist: pyopencl
Requires-Dist: mako
Requires-Dist: pycparser
Requires-Dist: pycparserext
Requires-Dist: pyastyle
Provides-Extra: dev
Requires-Dist: pytest ; extra == 'dev'
Requires-Dist: check-manifest ; extra == 'dev'
Requires-Dist: twine ; extra == 'dev'
Requires-Dist: wheel ; extra == 'dev'
